ocsp_responder_server/OCSP_server.py
ocsp_responder_server/__init__.py
ocsp_responder_server/rpc_server_request.py
ocsp_responder_server-0.5.dist-info/LICENSE
ocsp_responder_server-0.5.dist-info/METADATA
ocsp_responder_server-0.5.dist-info/WHEEL
ocsp_responder_server-0.5.dist-info/top_level.txt
ocsp_responder_server-0.5.dist-info/RECORD
