Metadata-Version: 2.1
Name: ocsp-responder-server
Version: 0.5
Summary: Simple OCSP Responder RPC Server
Home-page: https://github.com/deborahjalfont/ocsp-responder-server
Author: Deborah Jalfon
Author-email: deborah.jalfon@redis.com
License: MIT
Keywords: ocsp,responder,server
Classifier: Development Status :: 3 - Alpha
Classifier: Intended Audience :: Developers
Classifier: Topic :: Software Development :: Build Tools
Classifier: License :: OSI Approved :: MIT License
License-File: LICENSE
Requires-Dist: json-rpc
Requires-Dist: werkzeug
Requires-Dist: pyopenssl (==22.1.0)
Requires-Dist: cryptography (==38.0.4)
Requires-Dist: openssl-ocsp-responder
